lib_youtube_cd_burner/__init__.py
lib_youtube_cd_burner/__main__.py
lib_youtube_cd_burner/lib_youtube_cd_burner/__init__.py
lib_youtube_cd_burner/lib_youtube_cd_burner/__main__.py
lib_youtube_cd_burner/lib_youtube_cd_burner/cd.py
lib_youtube_cd_burner/lib_youtube_cd_burner/playlist.py
lib_youtube_cd_burner/lib_youtube_cd_burner/song.py
lib_youtube_cd_burner/lib_youtube_cd_burner/utils/__init__.py
lib_youtube_cd_burner/lib_youtube_cd_burner/utils/logger.py
lib_youtube_cd_burner/lib_youtube_cd_burner/utils/utils.py
lib_youtube_cd_burner/lib_youtube_cd_burner/utils/youtube_dl_fix.py
lib_youtube_cd_burner/static/main.css
lib_youtube_cd_burner/templates/home.html
lib_youtube_cd_burner/templates/layout.html
lib_youtube_cd_burner-0.2.1.dist-info/LICENSE
lib_youtube_cd_burner-0.2.1.dist-info/METADATA
lib_youtube_cd_burner-0.2.1.dist-info/WHEEL
lib_youtube_cd_burner-0.2.1.dist-info/entry_points.txt
lib_youtube_cd_burner-0.2.1.dist-info/top_level.txt
lib_youtube_cd_burner-0.2.1.dist-info/RECORD
