Metadata-Version: 2.1
Name: lib-youtube-cd-burner
Version: 0.2.1
Summary: Downloads youtube playlists and saves or formats them
Home-page: https://github.com/jfuruness/lib_youtube_cd_burner.git
Author: UNKNOWN
Author-email: UNKNOWN
License: BSD
Download-URL: https://github.com/jfuruness/lib_youtube_cd_burner.git
Keywords: Furuness,cd,burner,youtube,audio,audio cd
Platform: UNKNOWN
Classifier: Environment :: Console
Classifier: Environment :: Web Environment
Classifier: Intended Audience :: Developers
Classifier: License :: OSI Approved :: MIT License
Classifier: Operating System :: POSIX :: Linux
Classifier: Programming Language :: Python :: 3
Requires-Dist: setuptools
Requires-Dist: youtube-dl
Requires-Dist: Flask
Requires-Dist: mutagen
Requires-Dist: numpy
Requires-Dist: WTForms
Requires-Dist: Flask-WTF
Requires-Dist: pydub
Requires-Dist: soundfile
